avito_api/__init__.py
avito_api/config.py
avito_api/exceptions.py
avito_api/utils.py
avito_api/auth/__init__.py
avito_api/auth/client.py
avito_api/auth/models.py
avito_api/client/__init__.py
avito_api/client/async_.py
avito_api/client/base.py
avito_api/client/sync.py
avito_api/item/__init__.py
avito_api/item/client.py
avito_api/item/models.py
avito_api/messenger/__init__.py
avito_api/messenger/client.py
avito_api/messenger/models.py
avito_api/user/__init__.py
avito_api/user/client.py
avito_api/user/models.py
avito_api-0.5.0.dist-info/licenses/LICENSE
tests/__init__.py
tests/conftest.py
tests/test_auth.py
tests/test_client.py
tests/test_messenger.py
avito_api-0.5.0.dist-info/METADATA
avito_api-0.5.0.dist-info/WHEEL
avito_api-0.5.0.dist-info/top_level.txt
avito_api-0.5.0.dist-info/RECORD
